codealert/CodeAlert.py
codealert/__init__.py
codealert-1.0.3b1.dist-info/DESCRIPTION.rst
codealert-1.0.3b1.dist-info/METADATA
codealert-1.0.3b1.dist-info/RECORD
codealert-1.0.3b1.dist-info/WHEEL
codealert-1.0.3b1.dist-info/metadata.json
codealert-1.0.3b1.dist-info/top_level.txt
